abs_nosql_charts_core/repository/base_repository.py
abs_nosql_charts_core/schema/base_schema.py
abs_nosql_charts_core/schema/charts_schema.py
abs_nosql_charts_core-0.3.1.dist-info/METADATA
abs_nosql_charts_core-0.3.1.dist-info/WHEEL
abs_nosql_charts_core-0.3.1.dist-info/RECORD
