Metadata-Version: 2.3
Name: abs-nosql-charts-core
Version: 0.3.1
Summary: A dashboard core library that provide all dashboard related base classes and utilities
Author: divy551
Author-email: divydedakiya5@gmail.com
Requires-Python: >=3.11,<4.0
Classifier: Programming Language :: Python :: 3
Classifier: Programming Language :: Python :: 3.11
Classifier: Programming Language :: Python :: 3.12
Classifier: Programming Language :: Python :: 3.13
Requires-Dist: abs-nosql-repository-core (>=0.11.3,<0.12.0)
